pycodamath/__init__.py
pycodamath/extra.py
pycodamath/pca.py
pycodamath/plot.py
pycodamath/pycoda.py
pyCoDaMath-1.0.dist-info/LICENSE
pyCoDaMath-1.0.dist-info/METADATA
pyCoDaMath-1.0.dist-info/WHEEL
pyCoDaMath-1.0.dist-info/top_level.txt
pyCoDaMath-1.0.dist-info/RECORD
