Metadata-Version: 2.1
Name: pyCoDaMath
Version: 1.0
Summary: Compositional data (CoDa) analysis tools for Python
Author-email: Christian Brinch <cbri@food.dtu.dk>
Project-URL: Homepage, https://bitbucket.org/genomicepidemiology/pycodamath
Project-URL: Bug Tracker, https://bitbucket.org/genomicepidemiology/pycodamath/issues?status=new&status=open&is_spam=!spam
Classifier: Programming Language :: Python :: 3
Classifier: License :: OSI Approved :: MIT License
Classifier: Operating System :: OS Independent
Requires-Python: >=3.7
License-File: LICENSE
Requires-Dist: matplotlib (>=3.1.1)
Requires-Dist: numpy (>=1.17.2)
Requires-Dist: pandas (>=0.25.1)
Requires-Dist: python-ternary (>=1.0.6)
Requires-Dist: scipy (>=1.3.1)
Requires-Dist: webcolors (>=1.13)
Requires-Dist: adjustText (==0.7.3)
